crx_hslayers/__init__.py
crx_hslayers/blocks.py
crx_hslayers/npm.py
crx_hslayers/widgets.py
crx_hslayers/static/package.json
crx_hslayers/static/clima-map/3rdpartylicenses.txt
crx_hslayers/static/clima-map/favicon.ico
crx_hslayers/static/clima-map/main-es2015.64f1dc2ab66ef26f31ea.js
crx_hslayers/static/clima-map/main-es2015.64f1dc2ab66ef26f31ea.js.map
crx_hslayers/static/clima-map/main-es5.64f1dc2ab66ef26f31ea.js
crx_hslayers/static/clima-map/main-es5.64f1dc2ab66ef26f31ea.js.map
crx_hslayers/static/clima-map/polyfills-es2015.5f9fcbce291e11651a1b.js
crx_hslayers/static/clima-map/polyfills-es2015.5f9fcbce291e11651a1b.js.map
crx_hslayers/static/clima-map/polyfills-es5.297307d84c99919d465f.js
crx_hslayers/static/clima-map/polyfills-es5.297307d84c99919d465f.js.map
crx_hslayers/static/clima-map/runtime-es2015.6c3271f44092b6637fc0.js
crx_hslayers/static/clima-map/runtime-es2015.6c3271f44092b6637fc0.js.map
crx_hslayers/static/clima-map/runtime-es5.6c3271f44092b6637fc0.js
crx_hslayers/static/clima-map/runtime-es5.6c3271f44092b6637fc0.js.map
crx_hslayers/static/clima-map/stats.json
crx_hslayers/static/clima-map/assets/hslayers-ng/img/ajax-loader.gif
crx_hslayers/static/clima-map/assets/hslayers-ng/img/blank.png
crx_hslayers/static/clima-map/assets/hslayers-ng/img/default.png
crx_hslayers/static/clima-map/assets/hslayers-ng/img/hslayers-ng-favicon_32x32.jpg
crx_hslayers/static/clima-map/assets/hslayers-ng/img/hslayers-ng-logo.png
crx_hslayers/static/clima-map/assets/hslayers-ng/img/notAvailable.png
crx_hslayers/static/clima-map/assets/hslayers-ng/img/orto.png
crx_hslayers/static/clima-map/assets/hslayers-ng/img/osm.png
crx_hslayers/static/clima-map/assets/hslayers-ng/img/pin_white_blue.png
crx_hslayers/static/clima-map/assets/hslayers-ng/img/pin_white_blue24.png
crx_hslayers/static/clima-map/assets/hslayers-ng/img/pin_white_blue32.png
crx_hslayers/static/clima-map/assets/hslayers-ng/img/pin_white_red32.png
crx_hslayers/static/clima-map/assets/hslayers-ng/img/tester.png
crx_hslayers-6.2.0.dist-info/METADATA
crx_hslayers-6.2.0.dist-info/WHEEL
crx_hslayers-6.2.0.dist-info/entry_points.txt
crx_hslayers-6.2.0.dist-info/top_level.txt
crx_hslayers-6.2.0.dist-info/RECORD
