Metadata-Version: 2.4
Name: crx_hslayers
Version: 6.2.0
Summary: HSLayers-NG integrated into Wagtail CMS with Codered
Author-email: Plan4All <h4e@lesprojekt.cz>
Project-URL: Homepage, https://github.com/hslayers/crx-hslayers
Project-URL: Bug Tracker, https://github.com/hslayers/crx-hslayers/issues
Classifier: Programming Language :: Python :: 3
Classifier: Intended Audience :: Developers
Classifier: Operating System :: OS Independent
Requires-Python: >=3.7
Requires-Dist: json5
Requires-Dist: coderedcms>=1.0.0
Requires-Dist: pynpm>=0.1.2
Requires-Dist: wagtail_crx_block_frontend_assets
